README.md
setup.cfg
setup.py
hackernews/__init__.py
hackernews/hn.py
hackernews/item.py
hackernews/user.py
hackernews_client.egg-info/PKG-INFO
hackernews_client.egg-info/SOURCES.txt
hackernews_client.egg-info/dependency_links.txt
hackernews_client.egg-info/requires.txt
hackernews_client.egg-info/top_level.txt