Metadata-Version: 2.1
Name: hackernews-client
Version: 0.1.2b1
Summary: An unofficial but simple Python client for Hacker News Web API.
Home-page: https://github.com/samisnotinsane/hackernews-client
Author: samisnotinsane
Author-email: sameen11@hotmail.com
License: MIT
Platform: UNKNOWN
Classifier: License :: OSI Approved :: MIT License
Classifier: Programming Language :: Python
Classifier: Programming Language :: Python :: 3
Classifier: Programming Language :: Python :: 3.6
Classifier: Programming Language :: Python :: Implementation :: CPython
Classifier: Programming Language :: Python :: Implementation :: PyPy
Requires-Python: >=3.6.0
